<?xml version="1.0" encoding="utf-8"?>
<PermissionSets>
  <PermissionSet RoleID="BINGMAPS SDK DEMO" RoleName="BingMaps SDK Demo">
    <Permission>
      <ObjectID>50250</ObjectID>
      <ObjectType>0</ObjectType>
      <ReadPermission>1</ReadPermission>
      <InsertPermission>1</InsertPermission>
      <ModifyPermission>1</ModifyPermission>
      <DeletePermission>1</DeletePermission>
      <ExecutePermission>0</ExecutePermission>
      <SecurityFilter />
    </Permission>
    <Permission>
      <ObjectID>50250</ObjectID>
      <ObjectType>1</ObjectType>
      <ReadPermission>0</ReadPermission>
      <InsertPermission>0</InsertPermission>
      <ModifyPermission>0</ModifyPermission>
      <DeletePermission>0</DeletePermission>
      <ExecutePermission>1</ExecutePermission>
      <SecurityFilter />
    </Permission>
    <Permission>
      <ObjectID>50251</ObjectID>
      <ObjectType>0</ObjectType>
      <ReadPermission>1</ReadPermission>
      <InsertPermission>1</InsertPermission>
      <ModifyPermission>1</ModifyPermission>
      <DeletePermission>1</DeletePermission>
      <ExecutePermission>0</ExecutePermission>
      <SecurityFilter />
    </Permission>
    <Permission>
      <ObjectID>50251</ObjectID>
      <ObjectType>1</ObjectType>
      <ReadPermission>0</ReadPermission>
      <InsertPermission>0</InsertPermission>
      <ModifyPermission>0</ModifyPermission>
      <DeletePermission>0</DeletePermission>
      <ExecutePermission>1</ExecutePermission>
      <SecurityFilter />
    </Permission>
    <Permission>
      <ObjectID>50250</ObjectID>
      <ObjectType>5</ObjectType>
      <ReadPermission>0</ReadPermission>
      <InsertPermission>0</InsertPermission>
      <ModifyPermission>0</ModifyPermission>
      <DeletePermission>0</DeletePermission>
      <ExecutePermission>1</ExecutePermission>
      <SecurityFilter />
    </Permission>
    <Permission>
      <ObjectID>50251</ObjectID>
      <ObjectType>5</ObjectType>
      <ReadPermission>0</ReadPermission>
      <InsertPermission>0</InsertPermission>
      <ModifyPermission>0</ModifyPermission>
      <DeletePermission>0</DeletePermission>
      <ExecutePermission>1</ExecutePermission>
      <SecurityFilter />
    </Permission>
    <Permission>
      <ObjectID>50250</ObjectID>
      <ObjectType>8</ObjectType>
      <ReadPermission>0</ReadPermission>
      <InsertPermission>0</InsertPermission>
      <ModifyPermission>0</ModifyPermission>
      <DeletePermission>0</DeletePermission>
      <ExecutePermission>1</ExecutePermission>
      <SecurityFilter />
    </Permission>
    <Permission>
      <ObjectID>50251</ObjectID>
      <ObjectType>8</ObjectType>
      <ReadPermission>0</ReadPermission>
      <InsertPermission>0</InsertPermission>
      <ModifyPermission>0</ModifyPermission>
      <DeletePermission>0</DeletePermission>
      <ExecutePermission>1</ExecutePermission>
      <SecurityFilter />
    </Permission>
    <Permission>
      <ObjectID>50258</ObjectID>
      <ObjectType>8</ObjectType>
      <ReadPermission>0</ReadPermission>
      <InsertPermission>0</InsertPermission>
      <ModifyPermission>0</ModifyPermission>
      <DeletePermission>0</DeletePermission>
      <ExecutePermission>1</ExecutePermission>
      <SecurityFilter />
    </Permission>
    <Permission>
      <ObjectID>50252</ObjectID>
      <ObjectType>8</ObjectType>
      <ReadPermission>0</ReadPermission>
      <InsertPermission>0</InsertPermission>
      <ModifyPermission>0</ModifyPermission>
      <DeletePermission>0</DeletePermission>
      <ExecutePermission>1</ExecutePermission>
      <SecurityFilter />
    </Permission>
    <Permission>
      <ObjectID>50256</ObjectID>
      <ObjectType>8</ObjectType>
      <ReadPermission>0</ReadPermission>
      <InsertPermission>0</InsertPermission>
      <ModifyPermission>0</ModifyPermission>
      <DeletePermission>0</DeletePermission>
      <ExecutePermission>1</ExecutePermission>
      <SecurityFilter />
    </Permission>
    <Permission>
      <ObjectID>50253</ObjectID>
      <ObjectType>8</ObjectType>
      <ReadPermission>0</ReadPermission>
      <InsertPermission>0</InsertPermission>
      <ModifyPermission>0</ModifyPermission>
      <DeletePermission>0</DeletePermission>
      <ExecutePermission>1</ExecutePermission>
      <SecurityFilter />
    </Permission>
    <Permission>
      <ObjectID>50254</ObjectID>
      <ObjectType>8</ObjectType>
      <ReadPermission>0</ReadPermission>
      <InsertPermission>0</InsertPermission>
      <ModifyPermission>0</ModifyPermission>
      <DeletePermission>0</DeletePermission>
      <ExecutePermission>1</ExecutePermission>
      <SecurityFilter />
    </Permission>
    <Permission>
      <ObjectID>50255</ObjectID>
      <ObjectType>8</ObjectType>
      <ReadPermission>0</ReadPermission>
      <InsertPermission>0</InsertPermission>
      <ModifyPermission>0</ModifyPermission>
      <DeletePermission>0</DeletePermission>
      <ExecutePermission>1</ExecutePermission>
      <SecurityFilter />
    </Permission>
    <Permission>
      <ObjectID>50257</ObjectID>
      <ObjectType>8</ObjectType>
      <ReadPermission>0</ReadPermission>
      <InsertPermission>0</InsertPermission>
      <ModifyPermission>0</ModifyPermission>
      <DeletePermission>0</DeletePermission>
      <ExecutePermission>1</ExecutePermission>
      <SecurityFilter />
    </Permission>
  </PermissionSet>
</PermissionSets>